tinyolap/__init__.py
tinyolap/area.py
tinyolap/authorization.py
tinyolap/cell.py
tinyolap/codemanager.py
tinyolap/commands.py
tinyolap/comments.py
tinyolap/config.py
tinyolap/cube.py
tinyolap/database.py
tinyolap/decorators.py
tinyolap/dimension.py
tinyolap/encryption.py
tinyolap/exceptions.py
tinyolap/facttable.py
tinyolap/history.py
tinyolap/logger.py
tinyolap/member.py
tinyolap/package.py
tinyolap/query.py
tinyolap/rules.py
tinyolap/server.py
tinyolap/slice.py
tinyolap/snapshot.py
tinyolap/users.py
tinyolap/view.py
tinyolap/storage/__init__.py
tinyolap/storage/backend.py
tinyolap/storage/mock.py
tinyolap/storage/sqlite.py
tinyolap/storage/storageprovider.py
tinyolap/utilities/__init__.py
tinyolap/utilities/case_insensitive_dict.py
tinyolap/utilities/file_management.py
tinyolap/utilities/hybrid_dict.py
tinyolap/utilities/utils.py
tinyolap-0.8.27.dist-info/LICENSE.txt
tinyolap-0.8.27.dist-info/METADATA
tinyolap-0.8.27.dist-info/WHEEL
tinyolap-0.8.27.dist-info/top_level.txt
tinyolap-0.8.27.dist-info/zip-safe
tinyolap-0.8.27.dist-info/RECORD
